ktb/__init__.py
ktb/constants.py
ktb/kinect.py
ktb/utils.py
ktb-0.0.1.dist-info/LICENSE
ktb-0.0.1.dist-info/METADATA
ktb-0.0.1.dist-info/WHEEL
ktb-0.0.1.dist-info/top_level.txt
ktb-0.0.1.dist-info/RECORD
