Metadata-Version: 2.1
Name: ktb
Version: 0.0.1
Summary: A python wrapper for the kinect built on pylibfreenect2
Home-page: https://github.com/nikwl/kinect-toolbox
Author: Nikolas lamb
Author-email: nil518@lehigh.edu
License: UNKNOWN
Platform: UNKNOWN
Classifier: Programming Language :: Python :: 3
Classifier: License :: OSI Approved :: GNU General Public License v2 (GPLv2)
Classifier: Operating System :: OS Independent
Classifier: Topic :: Multimedia :: Video :: Capture
Requires-Python: >=3.6
Requires-Dist: numpy
Requires-Dist: pylibfreenect2 (==0.1.3)
Requires-Dist: opencv-python (>=4.2.0.0)
